tvtk/misc.py
tvtk/tvtk_classes.zip
tvtk/version.py
tvtk/class_tree.py
tvtk/__init__.py
tvtk/code_gen.py
tvtk/indenter.py
tvtk/api.py
tvtk/common.py
tvtk/array_ext.cpython-39-darwin.so
tvtk/tvtk_base_handler.py
tvtk/wrapper_gen.py
tvtk/array_handler.py
tvtk/vtk_parser.py
tvtk/messenger.py
tvtk/tvtk_access.py
tvtk/special_gen.py
tvtk/tvtk_base.py
tvtk/value_column.py
tvtk/vtk_module.py
tvtk/_setup.py
tvtk/pipeline/__init__.py
tvtk/pipeline/browser.py
tvtk/pipeline/images/renderer.png
tvtk/pipeline/images/writer.png
tvtk/pipeline/images/reader.png
tvtk/pipeline/images/polydata.png
tvtk/pipeline/images/image_LICENSE.txt
tvtk/pipeline/images/actor.png
tvtk/pipeline/images/property.png
tvtk/pipeline/images/window.png
tvtk/pipeline/images/filter.png
tvtk/pipeline/images/coordinate.png
tvtk/pipeline/images/texture.png
tvtk/pipeline/images/rendererwindow.png
tvtk/pipeline/images/mapper.png
tvtk/pipeline/images/source.png
tvtk/pipeline/images/rendererwindowinteractor.png
tvtk/pipeline/images/camera.png
tvtk/pipeline/images/lookuptable.png
tvtk/tools/__init__.py
tvtk/tools/mlab.py
tvtk/tools/visual.py
tvtk/tools/ivtk.py
tvtk/tools/tvtk_doc.py
tvtk/tools/images/scene.ico
tvtk/tools/images/image_LICENSE.txt
tvtk/util/ctf.py
tvtk/util/traitsui_gradient_editor.py
tvtk/util/__init__.py
tvtk/util/wx_gradient_editor.py
tvtk/util/qt_gradient_editor.py
tvtk/util/tk_gradient_editor.py
tvtk/util/gradient_editor.py
tvtk/pyface/decorated_scene.py
tvtk/pyface/picker.py
tvtk/pyface/light_manager.py
tvtk/pyface/actor_editor.py
tvtk/pyface/toolkit.py
tvtk/pyface/scene_model.py
tvtk/pyface/__init__.py
tvtk/pyface/scene.py
tvtk/pyface/api.py
tvtk/pyface/movie_maker.py
tvtk/pyface/utils.py
tvtk/pyface/tvtk_scene.py
tvtk/pyface/scene_editor.py
tvtk/pyface/actors.py
tvtk/pyface/actor_model.py
tvtk/pyface/ui/__init__.py
tvtk/pyface/ui/wx/decorated_scene.py
tvtk/pyface/ui/wx/actor_editor.py
tvtk/pyface/ui/wx/__init__.py
mayavi_dev-4.8.3.dev0.dist-info/RECORD
mayavi_dev-4.8.3.dev0.dist-info/WHEEL
mayavi_dev-4.8.3.dev0.dist-info/entry_points.txt
mayavi_dev-4.8.3.dev0.dist-info/top_level.txt
mayavi_dev-4.8.3.dev0.dist-info/METADATA
mayavi_dev-4.8.3.dev0.dist-info/licenses/LICENSE_COLORBREWER.txt
mayavi_dev-4.8.3.dev0.dist-info/licenses/LICENSE_YORICK.txt
mayavi_dev-4.8.3.dev0.dist-info/licenses/LICENSE.txt
