Metadata-Version: 2.4
Name: mayavi-dev
Version: 4.8.3.dev0
Summary: 3D scientific data visualization library and application
Home-page: http://docs.enthought.com/mayavi/mayavi/
Download-URL: https://www.github.com/enthought/mayavi
Author: Prabhu Ramachandran, et al.
Author-email: prabhu@aero.iitb.ac.in
Maintainer: ETS Developers
Maintainer-email: mayavi-users@lists.sf.net
License: BSD
Platform: Windows
Platform: Linux
Platform: Mac OS-X
Platform: Unix
Platform: Solaris
Classifier: Development Status :: 5 - Production/Stable
Classifier: Intended Audience :: Developers
Classifier: Intended Audience :: Science/Research
Classifier: License :: OSI Approved :: BSD License
Classifier: Operating System :: MacOS
Classifier: Operating System :: Microsoft :: Windows
Classifier: Operating System :: OS Independent
Classifier: Operating System :: POSIX
Classifier: Operating System :: Unix
Classifier: Programming Language :: C
Classifier: Programming Language :: Python
Classifier: Topic :: Scientific/Engineering
Classifier: Topic :: Software Development
Classifier: Topic :: Software Development :: Libraries
Requires-Python: >=3.9
License-File: LICENSE.txt
License-File: LICENSE_COLORBREWER.txt
License-File: LICENSE_YORICK.txt
Requires-Dist: apptools
Requires-Dist: configobj
Requires-Dist: envisage
Requires-Dist: numpy
Requires-Dist: pyface>=6.1.1
Requires-Dist: pygments
Requires-Dist: traits>=6.0.0
Requires-Dist: traitsui>=7.0.0
Requires-Dist: packaging
Requires-Dist: importlib_resources; python_version < "3.11"
Requires-Dist: vtk
Requires-Dist: puremagic
Provides-Extra: app
Requires-Dist: envisage; extra == "app"
Dynamic: author
Dynamic: author-email
Dynamic: classifier
Dynamic: description
Dynamic: description-content-type
Dynamic: download-url
Dynamic: home-page
Dynamic: license
Dynamic: license-file
Dynamic: maintainer
Dynamic: maintainer-email
Dynamic: platform
Dynamic: provides-extra
Dynamic: requires-dist
Dynamic: requires-python
Dynamic: summary
